paramount/__init__.py
paramount/client/__init__.py
paramount/client/dist/__init__.py
paramount/client/dist/index.html
paramount/client/dist/vite.svg
paramount/client/dist/assets/__init__.py
paramount/client/dist/assets/index-Dh6UuDda.css
paramount/client/dist/assets/index-DzqpP7q_.js
paramount/server/__init__.py
paramount/server/api.py
paramount/server/cli.py
paramount/server/library_functions.py
paramount/server/record.py
paramount/server/wsgi.py
paramount/server/db_connector/__init__.py
paramount/server/db_connector/csv.py
paramount/server/db_connector/db.py
paramount/server/db_connector/postgres.py
paramount-0.4.0.dist-info/LICENSE
paramount-0.4.0.dist-info/METADATA
paramount-0.4.0.dist-info/WHEEL
paramount-0.4.0.dist-info/entry_points.txt
paramount-0.4.0.dist-info/top_level.txt
paramount-0.4.0.dist-info/RECORD
