Metadata-Version: 2.1
Name: paramount
Version: 0.4.0
Summary: Business Evals for LLMs
Home-page: https://github.com/ask-fini/paramount
Author: Hakim K
Author-email: 5586611+hakimkhalafi@users.noreply.github.com
Project-URL: Source Code, https://github.com/ask-fini/paramount
License-File: LICENSE
Requires-Dist: requests
Requires-Dist: pandas
Requires-Dist: pytz
Requires-Dist: flask
Requires-Dist: python-dotenv
Requires-Dist: scikit-learn
Requires-Dist: sqlalchemy
Requires-Dist: psycopg2-binary
Requires-Dist: gunicorn
Requires-Dist: toml
